openchaver/__init__.py
openchaver/__main__.py
openchaver/api.py
openchaver/const.py
openchaver/db.py
openchaver/logger.py
openchaver/monitor.py
openchaver/nudenet.py
openchaver/opennsfw.py
openchaver/services.py
openchaver/threads.py
openchaver/utils.py
openchaver/window.py
openchaver_client-0.4.1.dist-info/LICENSE
openchaver_client-0.4.1.dist-info/METADATA
openchaver_client-0.4.1.dist-info/WHEEL
openchaver_client-0.4.1.dist-info/entry_points.txt
openchaver_client-0.4.1.dist-info/top_level.txt
openchaver_client-0.4.1.dist-info/RECORD
