Metadata-Version: 2.1
Name: openchaver-client
Version: 0.4.1
Summary: An open source alternative to WebChaver.
Home-page: https://github.com/dickermoshe/OpenChaver
Author: Moshe Dicker
Author-email: mail@openchaver.com
License: GNU General Public License v3.0
Requires-Python: >=3.10
License-File: LICENSE
Requires-Dist: alembic (==1.8.1)
Requires-Dist: banal (==1.0.6)
Requires-Dist: certifi (==2022.9.24)
Requires-Dist: charset-normalizer (==2.1.1)
Requires-Dist: click (==8.1.3)
Requires-Dist: colorama (==0.4.5)
Requires-Dist: coloredlogs (==15.0.1)
Requires-Dist: dataset (==1.5.2)
Requires-Dist: Flask (==2.2.2)
Requires-Dist: flatbuffers (==22.9.24)
Requires-Dist: greenlet (==1.1.3.post0)
Requires-Dist: humanfriendly (==10.0)
Requires-Dist: idna (==3.4)
Requires-Dist: itsdangerous (==2.1.2)
Requires-Dist: Jinja2 (==3.1.2)
Requires-Dist: Mako (==1.2.3)
Requires-Dist: MarkupSafe (==2.1.1)
Requires-Dist: marshmallow (==3.18.0)
Requires-Dist: mpmath (==1.2.1)
Requires-Dist: mss (==6.1.0)
Requires-Dist: numpy (==1.23.4)
Requires-Dist: onnxruntime (==1.12.1)
Requires-Dist: opencv-python (==4.6.0.66)
Requires-Dist: oschmod (==0.3.12)
Requires-Dist: packaging (==21.3)
Requires-Dist: Pillow (==9.2.0)
Requires-Dist: protobuf (==4.21.8)
Requires-Dist: psutil (==5.9.3)
Requires-Dist: pyparsing (==3.0.9)
Requires-Dist: pyreadline3 (==3.4.1)
Requires-Dist: pywin32 (==304)
Requires-Dist: requests (==2.28.1)
Requires-Dist: SQLAlchemy (==1.4.42)
Requires-Dist: sympy (==1.11.1)
Requires-Dist: urllib3 (==1.26.12)
Requires-Dist: Werkzeug (==2.2.2)
